pynpb/__init__.py
pynpb/active_draft.py
pynpb/amateur_draft.py
pynpb/batting_stats.py
pynpb/fielding_stats.py
pynpb/pitching_stats.py
pynpb/player_data.py
pynpb/standings.py
pynpb/team_batting.py
pynpb/team_fielding.py
pynpb/team_pitching.py
pynpb/utils.py
pynpb/version.py
pynpb/data_helpers/__init__.py
pynpb/data_helpers/singleton.py
pynpb/data_sources/__init__.py
pynpb/data_sources/baseball_reference.py
pynpb-1.0.0.dist-info/LICENSE
pynpb-1.0.0.dist-info/METADATA
pynpb-1.0.0.dist-info/WHEEL
pynpb-1.0.0.dist-info/top_level.txt
pynpb-1.0.0.dist-info/RECORD
